mm_address_parser/__init__.py
mm_address_parser/parser.py
mm_address_parser/parser_utils.py
mm_address_parser-0.1.4.dist-info/licenses/LICENSE
mm_address_parser-0.1.4.dist-info/METADATA
mm_address_parser-0.1.4.dist-info/WHEEL
mm_address_parser-0.1.4.dist-info/top_level.txt
mm_address_parser-0.1.4.dist-info/RECORD
