Metadata-Version: 2.4
Name: mm_address_parser
Version: 0.1.4
Summary: A parser for Myanmar addresses
Author-email: myothida <mmdt@istarvz.com>
License-Expression: MIT
Project-URL: Homepage, https://github.com/myothida/mm_address_parser
Classifier: Programming Language :: Python :: 3
Classifier: Operating System :: OS Independent
Requires-Python: >=3.9
License-File: LICENSE
Requires-Dist: regex
Provides-Extra: dev
Requires-Dist: pytest; extra == "dev"
Requires-Dist: black; extra == "dev"
Requires-Dist: isort; extra == "dev"
Requires-Dist: mypy; extra == "dev"
Dynamic: license-file
